LICENSE
MANIFEST.in
README.md
setup.py
allauth_intersis/__init__.py
allauth_intersis/provider.py
allauth_intersis/urls.py
allauth_intersis/views.py
django_allauth_intersis.egg-info/PKG-INFO
django_allauth_intersis.egg-info/SOURCES.txt
django_allauth_intersis.egg-info/dependency_links.txt
django_allauth_intersis.egg-info/requires.txt
django_allauth_intersis.egg-info/top_level.txt